alpbench/__init__.py
alpbench/benchmark/ActiveLearningScenario.py
alpbench/benchmark/ActiveLearningSetting.py
alpbench/benchmark/BenchmarkConnector.py
alpbench/benchmark/BenchmarkSuite.py
alpbench/benchmark/Observer.py
alpbench/benchmark/__init__.py
alpbench/evaluation/__init__.py
alpbench/evaluation/analysis/__init__.py
alpbench/evaluation/analysis/generate_figs.py
alpbench/evaluation/analysis/get_results.py
alpbench/evaluation/analysis/get_results_ecai.py
alpbench/evaluation/analysis/plot_functions.py
alpbench/evaluation/analysis/plot_functions_for_ecai.py
alpbench/evaluation/analysis/visualize_results.py
alpbench/evaluation/experimenter/DefaultSetup.py
alpbench/evaluation/experimenter/Experimenter.py
alpbench/evaluation/experimenter/LogTableObserver.py
alpbench/evaluation/experimenter/Small.py
alpbench/evaluation/experimenter/__init__.py
alpbench/pipeline/ALPEvaluator.py
alpbench/pipeline/ActiveLearningPipeline.py
alpbench/pipeline/Initializer.py
alpbench/pipeline/Oracle.py
alpbench/pipeline/QueryStrategy.py
alpbench/pipeline/__init__.py
alpbench/util/TorchUtil.py
alpbench/util/__init__.py
alpbench/util/common.py
alpbench/util/ensemble_constructor.py
alpbench/util/transformer.py
alpbench/util/transformer_prediction_interface.py
alpbench/util/transformer_prediction_interface_ens.py
alpbench/util/pytorch_tabnet/__init__.py
alpbench/util/pytorch_tabnet/abstract_model.py
alpbench/util/pytorch_tabnet/augmentations.py
alpbench/util/pytorch_tabnet/callbacks.py
alpbench/util/pytorch_tabnet/metrics.py
alpbench/util/pytorch_tabnet/multiclass_utils.py
alpbench/util/pytorch_tabnet/multitask.py
alpbench/util/pytorch_tabnet/pretraining.py
alpbench/util/pytorch_tabnet/pretraining_utils.py
alpbench/util/pytorch_tabnet/sparsemax.py
alpbench/util/pytorch_tabnet/tab_model.py
alpbench/util/pytorch_tabnet/tab_network.py
alpbench/util/pytorch_tabnet/utils.py
alpbench-0.1.2.dist-info/METADATA
alpbench-0.1.2.dist-info/WHEEL
alpbench-0.1.2.dist-info/top_level.txt
alpbench-0.1.2.dist-info/zip-safe
alpbench-0.1.2.dist-info/RECORD
