Metadata-Version: 2.1
Name: alpbench
Version: 0.1.2
Summary: Active Learning Pipelines Benchmark
Home-page: https://github.com/ValentinMargraf/ActiveLearningPipelines
Author: Valentin Margraf et al.
Author-email: valentin.margraf@ifi.lmu.de
License: MIT
Project-URL: Tracker, https://github.com/ValentinMargraf/ActiveLearningPipelines/issues
Project-URL: Source, https://github.com/ValentinMargraf/ActiveLearningPipelines
Project-URL: Documentation, https://activelearningpipelines.readthedocs.io/
Keywords: python,machine learning,active learning,benchmark,tabular data,classification
Classifier: Development Status :: 4 - Beta
Classifier: License :: OSI Approved :: MIT License
Classifier: Intended Audience :: Developers
Classifier: Intended Audience :: Science/Research
Classifier: Topic :: Scientific/Engineering
Classifier: Topic :: Scientific/Engineering :: Artificial Intelligence
Classifier: Programming Language :: Python
Classifier: Programming Language :: Python :: 3.10
Classifier: Programming Language :: Python :: 3.11
Requires-Python: >=3.10.0
Requires-Dist: numpy
Requires-Dist: scipy
Requires-Dist: matplotlib
Requires-Dist: pandas
Requires-Dist: py-experimenter
Requires-Dist: mysql-connector-python
Requires-Dist: openml
Requires-Dist: scikit-learn
Requires-Dist: scikit-activeml
Requires-Dist: catboost
Requires-Dist: xgboost
Provides-Extra: full
Requires-Dist: numpy ; extra == 'full'
Requires-Dist: scipy ; extra == 'full'
Requires-Dist: matplotlib ; extra == 'full'
Requires-Dist: pandas ; extra == 'full'
Requires-Dist: py-experimenter ; extra == 'full'
Requires-Dist: mysql-connector-python ; extra == 'full'
Requires-Dist: openml ; extra == 'full'
Requires-Dist: scikit-learn ; extra == 'full'
Requires-Dist: scikit-activeml ; extra == 'full'
Requires-Dist: catboost ; extra == 'full'
Requires-Dist: xgboost ; extra == 'full'
Requires-Dist: pytorch-tabnet ; extra == 'full'
Requires-Dist: tabpfn ; extra == 'full'
